databrickslabs_jupyterlab/__init__.py
databrickslabs_jupyterlab/__main__.py
databrickslabs_jupyterlab/_version.py
databrickslabs_jupyterlab/connect.py
databrickslabs_jupyterlab/database.py
databrickslabs_jupyterlab/dbfs.py
databrickslabs_jupyterlab/install.py
databrickslabs_jupyterlab/kernel.py
databrickslabs_jupyterlab/local.py
databrickslabs_jupyterlab/mlflow.py
databrickslabs_jupyterlab/notebook.py
databrickslabs_jupyterlab/progress.py
databrickslabs_jupyterlab/remote.py
databrickslabs_jupyterlab/rest.py
databrickslabs_jupyterlab/ssh_config.py
databrickslabs_jupyterlab/utils.py
databrickslabs_jupyterlab/status/__init__.py
databrickslabs_jupyterlab/status/jupyter_notebook/databrickslabs_jupyterlab.json
databrickslabs_jupyterlab/status/jupyter_server/databrickslabs_jupyterlab.json
databrickslabs_jupyterlab-2.2.1.data/data/etc/jupyter/jupyter_server_config.d/databrickslabs_jupyterlab.json
databrickslabs_jupyterlab-2.2.1.data/scripts/databrickslabs-jupyterlab
databrickslabs_jupyterlab-2.2.1.data/scripts/dj
databrickslabs_jupyterlab-2.2.1.data/scripts/dj.bat
databrickslabs_jupyterlab-2.2.1.dist-info/LICENSE
databrickslabs_jupyterlab-2.2.1.dist-info/METADATA
databrickslabs_jupyterlab-2.2.1.dist-info/NOTICE
databrickslabs_jupyterlab-2.2.1.dist-info/WHEEL
databrickslabs_jupyterlab-2.2.1.dist-info/top_level.txt
databrickslabs_jupyterlab-2.2.1.dist-info/RECORD
